{"url": "https://answers.yahoo.com/question/index?qid=20091117170631AA82zvN", "question": "Weird stomach painssssssssssssss?", "question_content": "So I drank one beer and I had this HUGE stomach pain, and lately I really haven&#39;t been feeling myself at all, one second I&#39;m hot the next I&#39;m freezing. Also one minute I&quot;m mad the next i&#39;m sad i&#39;m all mixed up is this anything anyone has experienced ?? Do you think I could be pregnant?", "question_timestamp": "20091117170631", "followers": 0, "number_of_answers": 2, "categories": ["Health", "Women's Health"], "answers": [{"answer_content": "With you feeling hot and then freezing,  did you have a fever?  If so, then maybe you have an infection :S  or the flu.  Should get it checked out and also check out if you are pregnant.  Hope you feel better.", "author_link": "https://answers.yahoo.com/activity/questions?show=Npe6CeTcaa", "author_name": "?", "best": "false", "dislikes": "0", "likes": 0, "timestamp": "2009-11-17T17:17:23Z"}, {"answer_content": "it might just be your period", "author_link": "https://answers.yahoo.com/activity/questions?show=85c8501faae23fc3de23b45a1e6f4725aa", "author_name": "niki", "best": "false", "dislikes": "0", "likes": 0, "timestamp": "2009-11-17T17:15:20Z"}], "authorInfor": "none", "last_updata_data": "now"}