{"url": "https://answers.yahoo.com/question/index?qid=20100710155346AASEyRG", "question": "birth control question?", "question_content": "so my boyfriend is visiting next month, right when im supposed to get my period. im on yaz, so if i skip the sugar pills and go right to the next pack of active pills i will skip my period all together. \r\n\r\nif we have sex, will i bleed? i heard that having sex right around when you&#39;re supposed to get your period can induce the bleeding. will that still happen even if im taking the active pills in the next pack?", "question_timestamp": "20100710155346", "followers": 0, "number_of_answers": 2, "categories": ["Health", "Women's Health"], "answers": [{"answer_content": "You won&#39;t bleed unless you&#39;ve been skipping sugar pills for like 4 months or more", "author_link": "https://answers.yahoo.com/activity/questions?show=52db325887e37b7659b1309d18180d87aa", "author_name": "wermfud", "best": "true", "dislikes": "0", "likes": 0, "timestamp": "2010-07-10T16:04:41Z"}, {"answer_content": "no u wnt bleed any more or any less just have a towel and mkae sure hes not grossed out by the bleeding and u will be fine.", "author_link": "https://answers.yahoo.com/activity/questions?show=q6ZWfbQraa", "author_name": "CUTIE", "best": "false", "dislikes": "0", "likes": 0, "timestamp": "2010-07-10T23:00:41Z"}], "authorInfor": "none", "last_updata_data": "now"}